amxlogs/__init__.py
amxlogs-1.1.3.dist-info/LICENSE
amxlogs-1.1.3.dist-info/METADATA
amxlogs-1.1.3.dist-info/WHEEL
amxlogs-1.1.3.dist-info/top_level.txt
amxlogs-1.1.3.dist-info/RECORD
