Metadata-Version: 2.1
Name: amxlogs
Version: 1.1.3
Summary: finds, downloads, and clears logs from AMX devices using ftp
Home-page: https://github.com/logantv/amxlogs
Author: Logan Vaughn
License: UNKNOWN
Project-URL: Bug Tracker, https://github.com/logantv/amxlogs/issues
Platform: UNKNOWN
Classifier: Programming Language :: Python :: 3
Classifier: License :: OSI Approved :: MIT License
Classifier: Operating System :: OS Independent
Requires-Python: >=3.6
